.flake8
.gitignore
.travis.yml
README.rst
pylintrc
requirements.txt
runtests.py
setup.py
tox.ini
tests/__init__.py
tests/base.py
tests/test_documents.py
tests/test_images.py
tests/test_pages.py
tests/test_settings.py
tests/test_sites.py
tests/app/models.py
tests/app/settings.py
tests/app/urls.py
tests/app/migrations/0001_initial.py
tests/app/migrations/__init__.py
tests/import_data/documents/hello-world.txt
tests/import_data/images/floral.jpeg
tests/import_data/images/hidden doge sleeping whippet.jpg
tests/import_data/images/lazors.jpg
tests/import_data/images/stretmch.jpg
tests/import_data/images/suunn.jpg
wagtailimporter/__init__.py
wagtailimporter/serializer.py
wagtailimporter.egg-info/PKG-INFO
wagtailimporter.egg-info/SOURCES.txt
wagtailimporter.egg-info/dependency_links.txt
wagtailimporter.egg-info/requires.txt
wagtailimporter.egg-info/top_level.txt
wagtailimporter/management/__init__.py
wagtailimporter/management/commands/__init__.py
wagtailimporter/management/commands/import_pages.py