Metadata-Version: 1.1
Name: wagtailimporter
Version: 2.0.0
Summary: Wagtail module to load pages from Yaml
Home-page: https://github.com/squareweave/wagtailimporter
Author: Squareweave
Author-email: team@squareweave.com.au
License: BSD
Platform: UNKNOWN
Classifier: Development Status :: 4 - Beta
Classifier: Intended Audience :: Developers
Classifier: Programming Language :: Python :: 3
Classifier: Programming Language :: Python :: 3.3
Classifier: Programming Language :: Python :: 3.4
Classifier: Programming Language :: Python :: 3.5
Classifier: Programming Language :: Python :: 3.6
